

  [{
      "id":10,
      "type":"Article",
      "title": "Transforming Correctional Culture and Climate",  
      "createdOn": "2024-05-15"
    },
    {
      "id":10,
      "type":"Book",
      "title": "Domestic Radicalization and Violent Extremism",  
      "createdOn": "2024-05-17"
    },
    {
      "id":10,
      "type":"Article",
      "title": "Transforming Correctional Culture and Climate",  
      "createdOn": "2024-05-15"
    },
    {
      "id":10,
      "type":"Book",
      "title": "Domestic Radicalization and Violent Extremism",  
      "createdOn": "2024-05-17"
    },{
      "id":10,
      "type":"Article",
      "title": "Transforming Correctional Culture and Climate",  
      "createdOn": "2024-05-15"
    },
    {
      "id":10,
      "type":"Book",
      "title": "Domestic Radicalization and Violent Extremism",  
      "createdOn": "2024-05-17"
    },{
      "id":10,
      "type":"Article",
      "title": "Transforming Correctional Culture and Climate",  
      "createdOn": "2024-05-15"
    },
    {
      "id":11,
      "type":"Book",
      "title": "Domestic Radicalization and Violent Extremism",  
      "createdOn": "2024-05-17"
    },
    {
      "id":11,
      "type":"Book",
      "title": "Improving Analysis of “Trace DNA” Evidence",  
      "createdOn": "2024-04-15"
    },
    {
      "id":12,
      "type":"Article",
      "title": "Transforming Correctional Culture and Climate",  
      "createdOn": "2024-02-15"
    },
    {
      "id":13,
      "type":"Book",
      "title": "Police Crime Lab Accreditation Initiative",  
      "createdOn": "2024-03-15"
    }
  ]